bitalino_lsl/__init__.py
bitalino_lsl/bitaReader.py
bitalino_lsl/bitalinoLSL.py
bitalino_lsl/lslStreamer.py
bitalino_lsl/sharedResources.py
bitalino_lsl-0.0.3.dist-info/LICENSE.txt
bitalino_lsl-0.0.3.dist-info/METADATA
bitalino_lsl-0.0.3.dist-info/WHEEL
bitalino_lsl-0.0.3.dist-info/top_level.txt
bitalino_lsl-0.0.3.dist-info/RECORD
