Metadata-Version: 2.1
Name: bitalino-lsl
Version: 0.0.3
Summary: Python module to stream BITalino data though the Lab Streaming Layer (LSL)
Home-page: https://github.com/fsuarezj/bitalino-lsl
Author: Fernando Suarez Jimenez
Author-email: fsuarezj@gmail.com
License: UNKNOWN
Platform: UNKNOWN
Classifier: Programming Language :: Python :: 3
Classifier: Programming Language :: Python :: 2.7
Classifier: License :: OSI Approved :: GNU General Public License v3 (GPLv3)
Classifier: Operating System :: OS Independent
Classifier: Topic :: Scientific/Engineering :: Bio-Informatics
Requires-Dist: bitalino
Requires-Dist: future
Requires-Dist: pylsl
